main.v
module processor(
    input clk, reset,
    output [31:0] pc,
    input [31:0] instruction,
    output write_enable,
    output [31:0] address_to_mem, data_to_mem,
    input [31:0] data_from_mem
);

    // ? 
    wire branch_blt, branch_beq, branch_jal, branch_jalr, reg_write, mem_to_reg, mem_write, alu_src;
    wire [2:0] alu_control;
    wire [2:0] imm_control;



    wire [31:0] PCPLus4, ALUOut;
    wire BranchJalx = branch_jal | branch_jalr;

    //    PC
    wire [31:0] BranchTarget;
    // ALU
    wire lt, Zero;
    wire MuxPCSelect = (branch_blt & lt) | (branch_beq & Zero) | BranchJalx;
    // ? ?  ? ?
    wire [31:0] WD3;
    wire [31:0] PCNext;
    // ? 
    wire [31:0] SrcA, rd2;
    // ?  
    wire [31:0] ImmOp;
    // ? ?  ? ALU
    wire [31:0] SrcB;

    // ? Control Unit
    control_unit ctrl(
        instruction, 
        branch_blt, branch_beq, branch_jal, branch_jalr, 
        reg_write, mem_to_reg, mem_write, alu_src, 
        alu_control, imm_control
    );
    
    ALU AlUModule(alu_control, SrcA, SrcB, lt, Zero, ALUOut);

    registers Regs(
        instruction[19:15], instruction[24:20], instruction[11:7],
        WD3, reg_write, reset, clk, SrcA, rd2
    );

    ImmDecoder immdec(instruction[31:7], imm_control, ImmOp);

    //  PC
    PC MyPC(PCNext, pc, clk, reset); 

    Plus4 alu4(pc, PCPLus4);


    assign SrcB = (alu_src) ? ImmOp : rd2;
        //  
    assign address_to_mem = ALUOut;
    assign data_to_mem = rd2;
    assign write_enable = mem_write;
    assign WD3 = (mem_to_reg) ? data_from_mem 
                            : (BranchJalx ? PCPLus4 : ALUOut);
    assign BranchTarget = (branch_jalr) ? ALUOut : (pc + ImmOp);
    assign PCNext = (MuxPCSelect) ? BranchTarget : reset ? 0 : PCPLus4;

endmodule


module Plus4(input [31:0] pcin, output [31:0] out);
    assign out = pcin + 4;
endmodule    


module control_unit(
        input [31:0] inst,
        output reg branch_blt, branch_beq, branch_jal, branch_jalr,
        output reg reg_write, mem_to_reg, mem_write, alu_src,
        output reg [2:0] alu_control,
        output reg [2:0] imm_control
    );
    // ?  ? opcodes
    localparam OPCODE_RTYPE   = 7'b0110011;
    localparam OPCODE_ITYPE   = 7'b0010011;
    localparam OPCODE_LOAD    = 7'b0000011;
    localparam OPCODE_STORE   = 7'b0100011;
    localparam OPCODE_BRANCH  = 7'b1100011;
    localparam OPCODE_LUI     = 7'b0110111;
    localparam OPCODE_JAL     = 7'b1101111;
    localparam OPCODE_JALR    = 7'b1100111;
    localparam OPCODE_EXP     = 7'b0001011; //  

    // ?  ? alu_control
    localparam ALU_AND       = 3'b000;
    localparam ALU_SRL       = 3'b001;
    localparam ALU_ADD       = 3'b010;
    localparam ALU_SUB       = 3'b011;
    localparam ALU_EXPONENT  = 3'b100;
    localparam ALU_LUI       = 3'b101;
    localparam ALU_ETD       = 3'b111;

    always @(*) begin
        // ?  
        branch_blt   = 0;
        branch_beq   = 0;
        branch_jal   = 0;
        branch_jalr  = 0;
        reg_write    = 0;
        mem_to_reg   = 0;
        mem_write    = 0;
        alu_src      = 0;
        alu_control  = ALU_ADD; //  ?
        imm_control  = 3'b000;  //  ?

        case (inst[6:0])
            OPCODE_RTYPE: begin // R-type 
                reg_write = 1;
                case ({inst[31:25], inst[14:12]})
                    {7'b0000000, 3'b000}: alu_control = ALU_ADD; // add
                    {7'b0100000, 3'b000}: alu_control = ALU_SUB; // sub
                    {7'b0000000, 3'b111}: alu_control = ALU_AND; // and
                    {7'b0000000, 3'b101}: alu_control = ALU_SRL; // srl
                    {7'b0000000, 3'b110}: alu_control = ALU_ETD; // etd

                endcase
            end
            OPCODE_ITYPE: begin // I-type  
                reg_write   = 1;
                alu_src     = 1;
                imm_control = 3'b001; // I-type immediate
                case (inst[14:12])
                    3'b000: alu_control = ALU_ADD; // addi
                endcase
            end
            OPCODE_LOAD: begin // Load 
                if (inst[14:12] == 3'b010) begin // lw
                    reg_write   = 1;
                    mem_to_reg  = 1;
                    alu_src     = 1;
                    imm_control = 3'b001; // I-type immediate
                end
            end
            OPCODE_STORE: begin // Store 
                if (inst[14:12] == 3'b010) begin // sw
                    mem_write   = 1;
                    alu_src     = 1;
                    imm_control = 3'b010; // S-type immediate
                end
            end
            OPCODE_BRANCH: begin // Branch 
                imm_control = 3'b011; // B-type immediate
                alu_control = ALU_SUB; // ? ?
                case (inst[14:12])
                    3'b000: branch_beq = 1; // beq
                    3'b100: branch_blt = 1; // blt
                    default: ;
                endcase
            end
            
            OPCODE_LUI: begin // LUI
                reg_write   = 1;
                alu_src     = 1;
                imm_control = 3'b100; // U-type immediate
                alu_control = ALU_LUI; //  ALU ?  
            end
            OPCODE_JAL: begin // JAL
                branch_jal  = 1;
                reg_write   = 1;
                imm_control = 3'b101; // J-type immediate
            end
            OPCODE_JALR: begin // JALR
                branch_jalr = 1;
                reg_write   = 1;
                alu_src     = 1;
                imm_control = 3'b001; // I-type immediate
            end
            OPCODE_EXP: begin //   - ? 
                if (inst[14:12] == 3'b000 && inst[31:25] == 7'b0000000) begin
                    reg_write   = 1;
                    alu_control = ALU_EXPONENT; // ? ?   
                end
            end

        endcase
    end
endmodule


module registers(
        input [4:0] a1, a2, a3,
        input [31:0] wd3,
        input we, reset, clk,
        output reg [31:0] rd1, rd2
    );

    integer i;
    reg [31:0] data [31:0];

    //  ? (? )
    always @(*) begin
        rd1 = data[a1];
        rd2 = data[a2];
    end

    //  ? ? ?
    always @(posedge clk or posedge reset) begin
        if (reset) begin
            for(i = 0; i < 32; i = i + 1)
                data[i] <= 0;
        end else begin
            if (we == 1 && a3 != 0) begin
                data[a3] <= wd3;
            end
        end
    end
endmodule


module ALU (
        input [2:0] ALUControl, // 3-  
        input [31:0] SrcA, SrcB,
        output reg lt, Zero,
        output reg [31:0] ALUOut
    );
    integer i;
    always @(*) begin
        Zero = 0;
        lt = 0;
        case (ALUControl)
            3'b000: ALUOut = SrcA & SrcB;            // AND
            3'b001: ALUOut = SrcA >> SrcB;           // SRL
            3'b010: ALUOut = SrcA + SrcB;            // ADD
            3'b011: ALUOut = SrcA - SrcB;            // SUB beq blt
            3'b100: ALUOut = $signed (SrcA[30:23]) - 127;
            default: ALUOut = SrcB; // LUI
        endcase

        Zero = (ALUOut == 0);
        lt = ($signed(SrcA) < $signed(SrcB));
    end
endmodule


module ImmDecoder(
        input [31:7] inst,
        input [2:0] imm_control,
        output reg [31:0] ImmOp
    );
    always @(*) begin
        ImmOp = 0;
        case (imm_control)
            //
            3'b000: ImmOp = 0; // 

            3'b001: begin // I-type (addi, lw, jalr)
                ImmOp[11:0] = inst[31:20];
                ImmOp[31:12] = {20{inst[31]}};
            end

            3'b010: begin // S-type (sw)
                // Imm[11:0] = {inst[31:25], inst[11:7]}
                ImmOp[11:5] = inst[31:25];
                ImmOp[4:0] = inst[11:7];
                ImmOp[31:12] = {20{inst[31]}};
            end

            3'b011: begin // B-type (beq, blt)
                ImmOp[31:13] = {19{inst[31]}};
                ImmOp[12]    = inst[31];
                ImmOp[11]    = inst[7];
                ImmOp[10:5]  = inst[30:25];
                ImmOp[4:1]   = inst[11:8];
                ImmOp[0]     = 0; 
            end

            3'b100: begin // U-type (lui)
                ImmOp[31:12] = inst[31:12];
                ImmOp[11:0] = 12'b0;
            end

            3'b101: begin // J-type (jal)
                ImmOp[31:21] = {11{inst[31]}};
                ImmOp[20]    = inst[31];
                ImmOp[19:12] = inst[19:12];
                ImmOp[11]    = inst[20];
                ImmOp[10:1]  = inst[30:21];
                ImmOp[0]     = 0; 
            end
            default: ImmOp = 0;
        endcase
    end
endmodule

module PC(input [31:0] PCnext, output [31:0] out, input clk, reset );
    reg [31:0] data;
    assign out = data;
    always @(posedge clk or posedge reset) begin
        if (reset)
            data <= 0;
        else
            data <= PCnext;
    end
endmodule

memories.v
module testbench();
	reg         clk;
	reg         reset;
	wire [31:0] data_to_mem, address_to_mem;
	wire        write_enable;

	top simulated_system (clk, reset, data_to_mem, address_to_mem, write_enable);

	initial	begin
		$dumpfile("test");
		$dumpvars;
		reset<=1; # 2; reset<=0;
		#100;
		$writememh ("memfile_data_after_simulation.hex",simulated_system.dmem.RAM,0,63);
		$finish;
	end

	// generate clock
	always	begin
		clk<=1; # 1; clk<=0; # 1;
	end
endmodule


module top (	input         clk, reset,
		output [31:0] data_to_mem, address_to_mem,
		output        write_enable);

	wire [31:0] pc, instruction, data_from_mem;

	inst_mem  imem(pc[7:2], instruction);
	data_mem  dmem(clk, write_enable, address_to_mem, data_to_mem, data_from_mem);
	processor CPU(clk, reset, pc, instruction, write_enable, address_to_mem, data_to_mem, data_from_mem);
endmodule

//-------------------------------------------------------------------
module data_mem (input clk, we,
		 input  [31:0] address, wd,
		 output [31:0] rd);

	reg [31:0] RAM[1023:0];

	initial begin
		$readmemh ("memfile_data.hex",RAM,0,1023);
	end

	assign rd=RAM[address[31:2]]; // word aligned

	always @ (posedge clk)
		if (we)
			RAM[address[31:2]]<=wd;
endmodule

//-------------------------------------------------------------------
module inst_mem (input  [5:0]  address,
		 output [31:0] rd);

	reg [31:0] RAM[63:0];
	initial begin
		$readmemh ("memfile_inst.hex",RAM,0,11);
	end
	assign rd=RAM[address]; // word aligned
endmodule

test.vcd
$date
	Sat Dec  7 17:38:36 2024
$end
$version
	Icarus Verilog
$end
$timescale
	1s
$end
$scope module testbench $end
$var wire 1 ! write_enable $end
$var wire 32 " data_to_mem [31:0] $end
$var wire 32 # address_to_mem [31:0] $end
$var reg 1 $ clk $end
$var reg 1 % reset $end
$scope module simulated_system $end
$var wire 1 $ clk $end
$var wire 1 % reset $end
$var wire 1 ! write_enable $end
$var wire 32 & pc [31:0] $end
$var wire 32 ' instruction [31:0] $end
$var wire 32 ( data_to_mem [31:0] $end
$var wire 32 ) data_from_mem [31:0] $end
$var wire 32 * address_to_mem [31:0] $end
$scope module CPU $end
$var wire 1 + BranchJalx $end
$var wire 1 , MuxPCSelect $end
$var wire 32 - address_to_mem [31:0] $end
$var wire 1 $ clk $end
$var wire 32 . data_to_mem [31:0] $end
$var wire 1 % reset $end
$var wire 1 ! write_enable $end
$var wire 1 / reg_write $end
$var wire 32 0 rd2 [31:0] $end
$var wire 32 1 pc [31:0] $end
$var wire 1 2 mem_write $end
$var wire 1 3 mem_to_reg $end
$var wire 1 4 lt $end
$var wire 32 5 instruction [31:0] $end
$var wire 3 6 imm_control [2:0] $end
$var wire 32 7 data_from_mem [31:0] $end
$var wire 1 8 branch_jalr $end
$var wire 1 9 branch_jal $end
$var wire 1 : branch_blt $end
$var wire 1 ; branch_beq $end
$var wire 1 < alu_src $end
$var wire 3 = alu_control [2:0] $end
$var wire 1 > Zero $end
$var wire 32 ? WD3 [31:0] $end
$var wire 32 @ SrcB [31:0] $end
$var wire 32 A SrcA [31:0] $end
$var wire 32 B PCPLus4 [31:0] $end
$var wire 32 C PCNext [31:0] $end
$var wire 32 D ImmOp [31:0] $end
$var wire 32 E BranchTarget [31:0] $end
$var wire 32 F ALUOut [31:0] $end
$scope module AlUModule $end
$var wire 32 G SrcB [31:0] $end
$var wire 32 H SrcA [31:0] $end
$var wire 3 I ALUControl [2:0] $end
$var reg 32 J ALUOut [31:0] $end
$var reg 1 > Zero $end
$var reg 1 4 lt $end
$upscope $end
$scope module MyPC $end
$var wire 32 K PCnext [31:0] $end
$var wire 1 $ clk $end
$var wire 32 L out [31:0] $end
$var wire 1 % reset $end
$var reg 32 M data [31:0] $end
$upscope $end
$scope module Regs $end
$var wire 5 N a1 [4:0] $end
$var wire 5 O a2 [4:0] $end
$var wire 5 P a3 [4:0] $end
$var wire 1 $ clk $end
$var wire 1 % reset $end
$var wire 32 Q wd3 [31:0] $end
$var wire 1 / we $end
$var reg 32 R rd1 [31:0] $end
$var reg 32 S rd2 [31:0] $end
$var integer 32 T i [31:0] $end
$upscope $end
$scope module alu4 $end
$var wire 32 U pcin [31:0] $end
$var wire 32 V out [31:0] $end
$upscope $end
$scope module ctrl $end
$var wire 32 W inst [31:0] $end
$var parameter 3 X ALU_ADD $end
$var parameter 3 Y ALU_AND $end
$var parameter 3 Z ALU_ETD $end
$var parameter 3 [ ALU_EXPONENT $end
$var parameter 3 \ ALU_LUI $end
$var parameter 3 ] ALU_SRL $end
$var parameter 3 ^ ALU_SUB $end
$var parameter 7 _ OPCODE_BRANCH $end
$var parameter 7 ` OPCODE_EXP $end
$var parameter 7 a OPCODE_ITYPE $end
$var parameter 7 b OPCODE_JAL $end
$var parameter 7 c OPCODE_JALR $end
$var parameter 7 d OPCODE_LOAD $end
$var parameter 7 e OPCODE_LUI $end
$var parameter 7 f OPCODE_RTYPE $end
$var parameter 7 g OPCODE_STORE $end
$var reg 3 h alu_control [2:0] $end
$var reg 1 < alu_src $end
$var reg 1 ; branch_beq $end
$var reg 1 : branch_blt $end
$var reg 1 9 branch_jal $end
$var reg 1 8 branch_jalr $end
$var reg 3 i imm_control [2:0] $end
$var reg 1 3 mem_to_reg $end
$var reg 1 2 mem_write $end
$var reg 1 / reg_write $end
$upscope $end
$scope module immdec $end
$var wire 3 j imm_control [2:0] $end
$var wire 25 k inst [31:7] $end
$var reg 32 l ImmOp [31:0] $end
$upscope $end
$upscope $end
$scope module dmem $end
$var wire 32 m address [31:0] $end
$var wire 1 $ clk $end
$var wire 32 n rd [31:0] $end
$var wire 32 o wd [31:0] $end
$var wire 1 ! we $end
$upscope $end
$scope module imem $end
$var wire 6 p address [5:0] $end
$var wire 32 q rd [31:0] $end
$upscope $end
$upscope $end
$upscope $end
$enddefinitions $end
$comment Show the parameter values. $end
$dumpall
b100011 g
b110011 f
b110111 e
b11 d
b1100111 c
b1101111 b
b10011 a
b1011 `
b1100011 _
b11 ^
b1 ]
b101 \
b100 [
b111 Z
b0 Y
b10 X
$end
#0
$dumpvars
b10000000010001010000011 q
b0 p
b0 o
b10000000000010000000000001000 n
b100 m
b100 l
b1000000001000101 k
b1 j
b1 i
b10 h
b10000000010001010000011 W
b100 V
b0 U
b100000 T
b0 S
b0 R
b10000000000010000000000001000 Q
b101 P
b100 O
b0 N
b0 M
b0 L
b0 K
b100 J
b10 I
b0 H
b100 G
b100 F
b100 E
b100 D
b0 C
b100 B
b0 A
b100 @
b10000000000010000000000001000 ?
0>
b10 =
1<
0;
0:
09
08
b10000000000010000000000001000 7
b1 6
b10000000010001010000011 5
14
13
02
b0 1
b0 0
1/
b0 .
b100 -
0,
0+
b100 *
b10000000000010000000000001000 )
b0 (
b10000000010001010000011 '
b0 &
1%
1$
b100 #
b0 "
0!
$end
#1
0$
#2
b100 C
b100 K
1$
0%
#3
0$
#4
b1000001001000000000000000000000 ?
b1000001001000000000000000000000 Q
b1000001001000000000000000000000 )
b1000001001000000000000000000000 7
b1000001001000000000000000000000 n
b1000 #
b1000 *
b1000 -
b1000 m
b1000 F
b1000 J
14
b1000 @
b1000 G
b1000 D
b1000 l
b1000 C
b1000 K
b10000000001000110 k
b110 P
b1000 O
b1 6
b1 i
b1 j
1<
13
1/
b1100 E
b100000000010001100000011 '
b100000000010001100000011 5
b100000000010001100000011 W
b100000000010001100000011 q
b1 p
b1000 B
b1000 V
b100 &
b100 1
b100 L
b100 M
b100 U
1$
#5
0$
#6
0,
bx )
bx 7
bx n
b10000000000010000000000001000 "
b10000000000010000000000001000 (
b10000000000010000000000001000 .
b10000000000010000000000001000 o
b10000000000010000000000001000 0
b10000000000010000000000001000 S
0>
b11101111111111101111111111111000 #
b11101111111111101111111111111000 *
b11101111111111101111111111111000 -
b11101111111111101111111111111000 m
b11101111111111101111111111111000 F
b11101111111111101111111111111000 J
14
b11100 D
b11100 l
b10000000000010000000000001000 @
b10000000000010000000000001000 G
b11101111111111101111111111111000 ?
b11101111111111101111111111111000 Q
b1100 C
b1100 K
b1010000000011100 k
b11100 P
b101 O
1;
b11 =
b11 I
b11 h
b11 6
b11 i
b11 j
0<
03
0/
b100100 E
b10100000000111001100011 '
b10100000000111001100011 5
b10100000000111001100011 W
b10100000000111001100011 q
b10 p
b1100 B
b1100 V
b1000 &
b1000 1
b1000 L
b1000 M
b1000 U
1$
#7
0$
#8
b0 "
b0 (
b0 .
b0 o
b0 0
b0 S
b1000001001000000000000000000000 A
b1000001001000000000000000000000 H
b1000001001000000000000000000000 R
b0 @
b0 G
bx ?
bx Q
b0 D
b0 l
b1000001001000000000000000000000 #
b1000001001000000000000000000000 *
b1000001001000000000000000000000 -
b1000001001000000000000000000000 m
b1000001001000000000000000000000 F
b1000001001000000000000000000000 J
04
b10000 C
b10000 K
b11001001010 k
b1010 P
b0 O
b110 N
1<
13
1/
b1 6
b1 i
b1 j
b10 =
b10 I
b10 h
0;
b1100 E
b110010010100000011 '
b110010010100000011 5
b110010010100000011 W
b110010010100000011 q
b11 p
b10000 B
b10000 V
b1100 &
b1100 1
b1100 L
b1100 M
b1100 U
1$
#9
0$
#10
b11 )
b11 7
b11 n
1>
b0 #
b0 *
b0 -
b0 m
b0 F
b0 J
1,
b0 A
b0 H
b0 R
1+
b11000 D
b11000 l
b10100 ?
b10100 Q
b101000 C
b101000 K
b110000000000000001 k
b1 P
b11000 O
b0 N
19
b101 6
b101 i
b101 j
0<
03
1/
b101000 E
b1100000000000000011101111 '
b1100000000000000011101111 5
b1100000000000000011101111 W
b1100000000000000011101111 q
b100 p
b10100 B
b10100 V
b10000 &
b10000 1
b10000 L
b10000 M
b10000 U
1$
#11
0$
#12
x4
bx )
bx 7
bx n
0,
bx A
bx H
bx R
bx #
bx *
bx -
bx m
bx F
bx J
x>
b0 D
b0 l
0+
bx ?
bx Q
b101100 C
b101100 K
b101000001010 k
b1010 P
b0 O
b1010 N
b100 =
b100 I
b100 h
b0 6
b0 i
b0 j
1/
09
b101000 E
b1010000010100001011 '
b1010000010100001011 5
b1010000010100001011 W
b1010000010100001011 q
b1010 p
b101100 B
b101100 V
b101000 &
b101000 1
b101000 L
b101000 M
b101000 U
1$
#13
0$
#14
b0 )
b0 7
b0 n
b110000 ?
b110000 Q
b10100 #
b10100 *
b10100 -
b10100 m
b10100 F
b10100 J
1,
b10100 A
b10100 H
b10100 R
1+
04
0>
b10100 C
b10100 K
b100000000 k
b0 P
b1 N
b1 6
b1 i
b1 j
1<
18
b10 =
b10 I
b10 h
1/
b10100 E
b1000000001100111 '
b1000000001100111 5
b1000000001100111 W
b1000000001100111 q
b1011 p
b110000 B
b110000 V
b101100 &
b101100 1
b101100 L
b101100 M
b101100 U
1$
#15
0$
#16
bx )
bx 7
bx n
b11000 C
b11000 K
b1000001001000000000000000000000 #
b1000001001000000000000000000000 *
b1000001001000000000000000000000 -
b1000001001000000000000000000000 m
b1000001001000000000000000000000 F
b1000001001000000000000000000000 J
0,
bx "
bx (
bx .
bx o
bx 0
bx S
b1000001001000000000000000000000 A
b1000001001000000000000000000000 H
b1000001001000000000000000000000 R
0+
b1000001001000000000000000000000 ?
b1000001001000000000000000000000 Q
b10100011001000000 k
b1010 O
b110 N
1!
12
b10 6
b10 i
b10 j
1<
0/
08
b101000110010000000100011 '
b101000110010000000100011 5
b101000110010000000100011 W
b101000110010000000100011 q
b101 p
b11000 B
b11000 V
b10100 &
b10100 1
b10100 L
b10100 M
b10100 U
1$
#17
0$
#18
b1000001001000000000000000000100 ?
b1000001001000000000000000000100 Q
b1000001001000000000000000000100 #
b1000001001000000000000000000100 *
b1000001001000000000000000000100 -
b1000001001000000000000000000100 m
b1000001001000000000000000000100 F
b1000001001000000000000000000100 J
b100 @
b100 G
b0 "
b0 (
b0 .
b0 o
b0 0
b0 S
b100 D
b100 l
b11100 C
b11100 K
b1000011000000110 k
b110 P
b100 O
1/
b1 6
b1 i
b1 j
1<
0!
02
b11100 E
b10000110000001100010011 '
b10000110000001100010011 5
b10000110000001100010011 W
b10000110000001100010011 q
b110 p
b11100 B
b11100 V
b11000 &
b11000 1
b11000 L
b11000 M
b11000 U
1$
#19
0$
#20
b10000000000010000000000000111 ?
b10000000000010000000000000111 Q
b11111111111111111111111111111111 @
b11111111111111111111111111111111 G
b11111111111111111111111111111111 D
b11111111111111111111111111111111 l
b10000000000010000000000000111 #
b10000000000010000000000000111 *
b10000000000010000000000000111 -
b10000000000010000000000000111 m
b10000000000010000000000000111 F
b10000000000010000000000000111 J
b100000 C
b100000 K
b1111111111110010100000101 k
b101 P
b11111 O
b101 N
b1 6
b1 i
b1 j
1<
1/
b10000000000010000000000001000 A
b10000000000010000000000001000 H
b10000000000010000000000001000 R
b11011 E
b11111111111100101000001010010011 '
b11111111111100101000001010010011 5
b11111111111100101000001010010011 W
b11111111111100101000001010010011 q
b111 p
b100000 B
b100000 V
b11100 &
b11100 1
b11100 L
b11100 M
b11100 U
1$
#21
0$
#22
b11 )
b11 7
b11 n
1,
1>
b100100 ?
b100100 Q
1+
b11111111111111111111111111101000 D
b11111111111111111111111111101000 l
b0 @
b0 G
b1000 C
b1000 K
b1111111010011111111100000 k
b0 P
b1001 O
b11111 N
19
b101 6
b101 i
b101 j
0<
1/
b0 #
b0 *
b0 -
b0 m
b0 F
b0 J
b1000 E
b11111110100111111111000001101111 '
b11111110100111111111000001101111 5
b11111110100111111111000001101111 W
b11111110100111111111000001101111 q
b1000 p
b0 A
b0 H
b0 R
b100100 B
b100100 V
b100000 &
b100000 1
b100000 L
b100000 M
b100000 U
1$
#23
0$
#24
bx )
bx 7
bx n
14
b11101111111111101111111111111001 #
b11101111111111101111111111111001 *
b11101111111111101111111111111001 -
b11101111111111101111111111111001 m
b11101111111111101111111111111001 F
b11101111111111101111111111111001 J
b10000000000010000000000000111 @
b10000000000010000000000000111 G
0,
b10000000000010000000000000111 "
b10000000000010000000000000111 (
b10000000000010000000000000111 .
b10000000000010000000000000111 o
b10000000000010000000000000111 0
b10000000000010000000000000111 S
0>
b11100 D
b11100 l
0+
b11101111111111101111111111111001 ?
b11101111111111101111111111111001 Q
b1100 C
b1100 K
b1010000000011100 k
b11100 P
b101 O
b0 N
1;
b11 =
b11 I
b11 h
b11 6
b11 i
b11 j
0/
09
b100100 E
b10100000000111001100011 '
b10100000000111001100011 5
b10100000000111001100011 W
b10100000000111001100011 q
b10 p
b1100 B
b1100 V
b1000 &
b1000 1
b1000 L
b1000 M
b1000 U
1$
#25
0$
#26
b0 "
b0 (
b0 .
b0 o
b0 0
b0 S
b1000001001000000000000000000100 A
b1000001001000000000000000000100 H
b1000001001000000000000000000100 R
b0 @
b0 G
bx ?
bx Q
b0 D
b0 l
b1000001001000000000000000000100 #
b1000001001000000000000000000100 *
b1000001001000000000000000000100 -
b1000001001000000000000000000100 m
b1000001001000000000000000000100 F
b1000001001000000000000000000100 J
04
b10000 C
b10000 K
b11001001010 k
b1010 P
b0 O
b110 N
1<
13
1/
b1 6
b1 i
b1 j
b10 =
b10 I
b10 h
0;
b1100 E
b110010010100000011 '
b110010010100000011 5
b110010010100000011 W
b110010010100000011 q
b11 p
b10000 B
b10000 V
b1100 &
b1100 1
b1100 L
b1100 M
b1100 U
1$
#27
0$
#28
b11 )
b11 7
b11 n
1>
b0 #
b0 *
b0 -
b0 m
b0 F
b0 J
1,
b0 A
b0 H
b0 R
1+
b11000 D
b11000 l
b10100 ?
b10100 Q
b101000 C
b101000 K
b110000000000000001 k
b1 P
b11000 O
b0 N
19
b101 6
b101 i
b101 j
0<
03
1/
b101000 E
b1100000000000000011101111 '
b1100000000000000011101111 5
b1100000000000000011101111 W
b1100000000000000011101111 q
b100 p
b10100 B
b10100 V
b10000 &
b10000 1
b10000 L
b10000 M
b10000 U
1$
#29
0$
#30
x4
bx )
bx 7
bx n
0,
bx A
bx H
bx R
bx #
bx *
bx -
bx m
bx F
bx J
x>
b0 D
b0 l
0+
bx ?
bx Q
b101100 C
b101100 K
b101000001010 k
b1010 P
b0 O
b1010 N
b100 =
b100 I
b100 h
b0 6
b0 i
b0 j
1/
09
b101000 E
b1010000010100001011 '
b1010000010100001011 5
b1010000010100001011 W
b1010000010100001011 q
b1010 p
b101100 B
b101100 V
b101000 &
b101000 1
b101000 L
b101000 M
b101000 U
1$
#31
0$
#32
b0 )
b0 7
b0 n
b110000 ?
b110000 Q
b10100 #
b10100 *
b10100 -
b10100 m
b10100 F
b10100 J
1,
b10100 A
b10100 H
b10100 R
1+
04
0>
b10100 C
b10100 K
b100000000 k
b0 P
b1 N
b1 6
b1 i
b1 j
1<
18
b10 =
b10 I
b10 h
1/
b10100 E
b1000000001100111 '
b1000000001100111 5
b1000000001100111 W
b1000000001100111 q
b1011 p
b110000 B
b110000 V
b101100 &
b101100 1
b101100 L
b101100 M
b101100 U
1$
#33
0$
#34
bx )
bx 7
bx n
b11000 C
b11000 K
b1000001001000000000000000000100 #
b1000001001000000000000000000100 *
b1000001001000000000000000000100 -
b1000001001000000000000000000100 m
b1000001001000000000000000000100 F
b1000001001000000000000000000100 J
0,
bx "
bx (
bx .
bx o
bx 0
bx S
b1000001001000000000000000000100 A
b1000001001000000000000000000100 H
b1000001001000000000000000000100 R
0+
b1000001001000000000000000000100 ?
b1000001001000000000000000000100 Q
b10100011001000000 k
b1010 O
b110 N
1!
12
b10 6
b10 i
b10 j
1<
0/
08
b101000110010000000100011 '
b101000110010000000100011 5
b101000110010000000100011 W
b101000110010000000100011 q
b101 p
b11000 B
b11000 V
b10100 &
b10100 1
b10100 L
b10100 M
b10100 U
1$
#35
0$
#36
b1000001001000000000000000001000 ?
b1000001001000000000000000001000 Q
b1000001001000000000000000001000 #
b1000001001000000000000000001000 *
b1000001001000000000000000001000 -
b1000001001000000000000000001000 m
b1000001001000000000000000001000 F
b1000001001000000000000000001000 J
b100 @
b100 G
b0 "
b0 (
b0 .
b0 o
b0 0
b0 S
b100 D
b100 l
b11100 C
b11100 K
b1000011000000110 k
b110 P
b100 O
1/
b1 6
b1 i
b1 j
1<
0!
02
b11100 E
b10000110000001100010011 '
b10000110000001100010011 5
b10000110000001100010011 W
b10000110000001100010011 q
b110 p
b11100 B
b11100 V
b11000 &
b11000 1
b11000 L
b11000 M
b11000 U
1$
#37
0$
#38
b11111111111111111111111111111111 @
b11111111111111111111111111111111 G
b10000000000010000000000000110 ?
b10000000000010000000000000110 Q
b11111111111111111111111111111111 D
b11111111111111111111111111111111 l
b100000 C
b100000 K
b1111111111110010100000101 k
b101 P
b11111 O
b101 N
b1 6
b1 i
b1 j
1<
1/
b10000000000010000000000000110 #
b10000000000010000000000000110 *
b10000000000010000000000000110 -
b10000000000010000000000000110 m
b10000000000010000000000000110 F
b10000000000010000000000000110 J
b11011 E
b11111111111100101000001010010011 '
b11111111111100101000001010010011 5
b11111111111100101000001010010011 W
b11111111111100101000001010010011 q
b111 p
b10000000000010000000000000111 A
b10000000000010000000000000111 H
b10000000000010000000000000111 R
b100000 B
b100000 V
b11100 &
b11100 1
b11100 L
b11100 M
b11100 U
1$
#39
0$
#40
b11 )
b11 7
b11 n
b100100 ?
b100100 Q
1,
1>
1+
b11111111111111111111111111101000 D
b11111111111111111111111111101000 l
b0 @
b0 G
b0 #
b0 *
b0 -
b0 m
b0 F
b0 J
b1000 C
b1000 K
b1111111010011111111100000 k
b0 P
b1001 O
b11111 N
19
b101 6
b101 i
b101 j
0<
1/
b0 A
b0 H
b0 R
b1000 E
b11111110100111111111000001101111 '
b11111110100111111111000001101111 5
b11111110100111111111000001101111 W
b11111110100111111111000001101111 q
b1000 p
b100100 B
b100100 V
b100000 &
b100000 1
b100000 L
b100000 M
b100000 U
1$
#41
0$
#42
bx )
bx 7
bx n
14
b11101111111111101111111111111010 #
b11101111111111101111111111111010 *
b11101111111111101111111111111010 -
b11101111111111101111111111111010 m
b11101111111111101111111111111010 F
b11101111111111101111111111111010 J
b10000000000010000000000000110 @
b10000000000010000000000000110 G
0,
b10000000000010000000000000110 "
b10000000000010000000000000110 (
b10000000000010000000000000110 .
b10000000000010000000000000110 o
b10000000000010000000000000110 0
b10000000000010000000000000110 S
0>
b11100 D
b11100 l
0+
b11101111111111101111111111111010 ?
b11101111111111101111111111111010 Q
b1100 C
b1100 K
b1010000000011100 k
b11100 P
b101 O
b0 N
1;
b11 =
b11 I
b11 h
b11 6
b11 i
b11 j
0/
09
b100100 E
b10100000000111001100011 '
b10100000000111001100011 5
b10100000000111001100011 W
b10100000000111001100011 q
b10 p
b1100 B
b1100 V
b1000 &
b1000 1
b1000 L
b1000 M
b1000 U
1$
#43
0$
#44
b0 "
b0 (
b0 .
b0 o
b0 0
b0 S
b1000001001000000000000000001000 A
b1000001001000000000000000001000 H
b1000001001000000000000000001000 R
b0 @
b0 G
bx ?
bx Q
b0 D
b0 l
b1000001001000000000000000001000 #
b1000001001000000000000000001000 *
b1000001001000000000000000001000 -
b1000001001000000000000000001000 m
b1000001001000000000000000001000 F
b1000001001000000000000000001000 J
04
b10000 C
b10000 K
b11001001010 k
b1010 P
b0 O
b110 N
1<
13
1/
b1 6
b1 i
b1 j
b10 =
b10 I
b10 h
0;
b1100 E
b110010010100000011 '
b110010010100000011 5
b110010010100000011 W
b110010010100000011 q
b11 p
b10000 B
b10000 V
b1100 &
b1100 1
b1100 L
b1100 M
b1100 U
1$
#45
0$
#46
b11 )
b11 7
b11 n
1>
b0 #
b0 *
b0 -
b0 m
b0 F
b0 J
1,
b0 A
b0 H
b0 R
1+
b11000 D
b11000 l
b10100 ?
b10100 Q
b101000 C
b101000 K
b110000000000000001 k
b1 P
b11000 O
b0 N
19
b101 6
b101 i
b101 j
0<
03
1/
b101000 E
b1100000000000000011101111 '
b1100000000000000011101111 5
b1100000000000000011101111 W
b1100000000000000011101111 q
b100 p
b10100 B
b10100 V
b10000 &
b10000 1
b10000 L
b10000 M
b10000 U
1$
#47
0$
